{
  "name": "Get required signatures of protected branch",
  "enabledForApps": true,
  "method": "GET",
  "path": "/repos/:owner/:repo/branches/:branch/protection/required_signatures",
  "params": [
    {
      "name": "owner",
      "type": "string",
      "required": true,
      "description": "",
      "location": "url"
    },
    {
      "name": "repo",
      "type": "string",
      "required": true,
      "description": "",
      "location": "url"
    },
    {
      "name": "branch",
      "type": "string",
      "required": true,
      "description": "",
      "location": "url"
    }
  ],
  "description": "",
  "idName": "",
  "documentationUrl": "https://developer.github.com/v3/repos/branches/#get-required-signatures-of-protected-branch"
}
