{
  "name": "Get a single event",
  "enabledForApps": true,
  "method": "GET",
  "path": "/repos/:owner/:repo/issues/events/:event_id",
  "params": [
    {
      "name": "owner",
      "type": "string",
      "required": true,
      "description": "",
      "location": "url"
    },
    {
      "name": "repo",
      "type": "string",
      "required": true,
      "description": "",
      "location": "url"
    },
    {
      "name": "event_id",
      "type": "integer",
      "required": true,
      "description": "",
      "location": "url"
    }
  ],
  "description": "",
  "idName": "",
  "documentationUrl": "https://developer.github.com/v3/issues/events/#get-a-single-event"
}
